trc20_monitor/__init__.py
trc20_monitor/cli.py
trc20_monitor/adapters/__init__.py
trc20_monitor/adapters/database.py
trc20_monitor/adapters/notification.py
trc20_monitor/core/__init__.py
trc20_monitor/core/exceptions.py
trc20_monitor/core/models.py
trc20_monitor/core/monitor.py
trc20_monitor/implementations/__init__.py
trc20_monitor/implementations/console_notifier.py
trc20_monitor/implementations/file_notifier.py
trc20_monitor/implementations/memory_db.py
trc20_monitor/implementations/sqlite_db.py
trc20_monitor/implementations/webhook_notifier.py
trc20_monitor/utils/__init__.py
trc20_monitor/utils/retry.py
trc20_monitor/utils/tron.py
trc20_monitor/utils/validation.py
trc20_monitor/worker/__init__.py
trc20_monitor/worker/worker.py
trc20_monitor-0.1.0.dist-info/licenses/LICENSE
trc20_monitor-0.1.0.dist-info/METADATA
trc20_monitor-0.1.0.dist-info/WHEEL
trc20_monitor-0.1.0.dist-info/entry_points.txt
trc20_monitor-0.1.0.dist-info/top_level.txt
trc20_monitor-0.1.0.dist-info/RECORD
