Metadata-Version: 2.4
Name: trc20-monitor
Version: 0.1.0
Summary: Professional TRC20 transaction monitoring for Tron blockchain
Author-email: TRC20 Monitor Team <support@trc20monitor.com>
License: MIT
Project-URL: Homepage, https://github.com/kun-g/trc20-monitor
Project-URL: Documentation, https://trc20-monitor.readthedocs.io/
Project-URL: Repository, https://github.com/kun-g/trc20-monitor.git
Project-URL: Issues, https://github.com/kun-g/trc20-monitor/issues
Project-URL: Changelog, https://github.com/kun-g/trc20-monitor/blob/main/CHANGELOG.md
Keywords: tron,trc20,usdt,blockchain,monitoring,cryptocurrency
Classifier: Development Status :: 4 - Beta
Classifier: Intended Audience :: Developers
Classifier: Intended Audience :: Financial and Insurance Industry
Classifier: License :: OSI Approved :: MIT License
Classifier: Operating System :: OS Independent
Classifier: Programming Language :: Python :: 3
Classifier: Programming Language :: Python :: 3.8
Classifier: Programming Language :: Python :: 3.9
Classifier: Programming Language :: Python :: 3.10
Classifier: Programming Language :: Python :: 3.11
Classifier: Programming Language :: Python :: 3.12
Classifier: Topic :: Office/Business :: Financial
Classifier: Topic :: Software Development :: Libraries :: Python Modules
Classifier: Topic :: System :: Monitoring
Requires-Python: >=3.8.1
License-File: LICENSE
Requires-Dist: aiohttp>=3.8.0
Requires-Dist: aiofiles>=23.0.0
Requires-Dist: base58>=2.1.0
Requires-Dist: aiosqlite>=0.19.0
Provides-Extra: dev
Requires-Dist: pytest>=7.0.0; extra == "dev"
Requires-Dist: pytest-asyncio>=0.21.0; extra == "dev"
Requires-Dist: pytest-cov>=4.0.0; extra == "dev"
Requires-Dist: pytest-mock>=3.10.0; extra == "dev"
Requires-Dist: black>=23.0.0; extra == "dev"
Requires-Dist: isort>=5.12.0; extra == "dev"
Requires-Dist: flake8>=6.0.0; extra == "dev"
Requires-Dist: mypy>=1.0.0; extra == "dev"
Requires-Dist: pre-commit>=3.0.0; extra == "dev"
Provides-Extra: sqlalchemy
Requires-Dist: sqlalchemy[asyncio]>=2.0.0; extra == "sqlalchemy"
Requires-Dist: asyncpg>=0.28.0; extra == "sqlalchemy"
Requires-Dist: aiomysql>=0.2.0; extra == "sqlalchemy"
Provides-Extra: full
Requires-Dist: sqlalchemy[asyncio]>=2.0.0; extra == "full"
Requires-Dist: asyncpg>=0.28.0; extra == "full"
Requires-Dist: aiomysql>=0.2.0; extra == "full"
Dynamic: license-file
